dataset/__init__.py
dataset/manager.py
dataset_manager_py-0.1.1.dist-info/LICENSE
dataset_manager_py-0.1.1.dist-info/METADATA
dataset_manager_py-0.1.1.dist-info/WHEEL
dataset_manager_py-0.1.1.dist-info/top_level.txt
dataset_manager_py-0.1.1.dist-info/RECORD
