Metadata-Version: 2.1
Name: dataset-manager-py
Version: 0.1.1
Summary: Python wrapper over the HuggingFace datasets library that makes it easier to load and convert datasets.
Author-email: Matthew Dutton <matthewdutton1983@hotmail.co.uk>
Classifier: License :: OSI Approved :: Apache Software License
Classifier: Programming Language :: Python :: 3
Classifier: Programming Language :: Python :: 3.8
Classifier: Programming Language :: Python :: 3.9
Classifier: Programming Language :: Python :: 3.10
Classifier: Programming Language :: Python :: 3.11
License-File: LICENSE
Requires-Dist: datasets
